[
    {
        "internalName": "VorkathPlugin",
        "name": "Vorkath",
        "description": "Microbot Vorkath plugin",
        "tags": [
            "vorkath",
            "microbot"
        ],
        "version": "1.3.9",
        "minClientVersion": "1.9.9.1",
        "authors": [
            "Mocrosoft"
        ],
        "iconUrl": "https://chsami.github.io/Microbot-Hub/VorkathPlugin/assets/icon.png",
        "cardUrl": "https://chsami.github.io/Microbot-Hub/VorkathPlugin/assets/card.png",
        "disable": false,
        "sha256": "2175513fce57c0239b62d96d75d5e0c25d140586fbe4725d150dc86a0a06ea6c",
        "url": "https://nexus.microbot.cloud/repository/microbot-plugins/net/runelite/client/plugins/microbot/vorkathplugin/1.3.9/vorkathplugin-1.3.9.jar"
    },
    {
        "internalName": "AutoEssenceMiningPlugin",
        "name": "Essence Mining",
        "description": "Mines Rune/Pure Essence...",
        "tags": [
            "mining",
            "essence",
            "skilling"
        ],
        "version": "1.0.1",
        "minClientVersion": "1.9.8",
        "authors": [
            "Unknown"
        ],
        "iconUrl": "https://chsami.github.io/Microbot-Hub/AutoEssenceMiningPlugin/assets/icon.png",
        "cardUrl": "https://chsami.github.io/Microbot-Hub/AutoEssenceMiningPlugin/assets/card.png",
        "disable": false,
        "sha256": "431a460c5c17abc75f9ef7b0e1b6b975d49a3f78da287b4001440621bf1dc47b",
        "url": "https://nexus.microbot.cloud/repository/microbot-plugins/net/runelite/client/plugins/microbot/autoessenceminingplugin/1.0.1/autoessenceminingplugin-1.0.1.jar"
    },
    {
        "internalName": "MotherloadMinePlugin",
        "name": "MotherlodeMine",
        "description": "A bot that mines paydirt in the motherlode mine",
        "tags": [
            "paydirt",
            "mine",
            "motherlode",
            "mlm"
        ],
        "version": "1.8.1",
        "minClientVersion": "1.9.8",
        "authors": [
            "Mocrosoft"
        ],
        "iconUrl": "https://chsami.github.io/Microbot-Hub/MotherloadMinePlugin/assets/icon.png",
        "cardUrl": "https://chsami.github.io/Microbot-Hub/MotherloadMinePlugin/assets/card.png",
        "disable": false,
        "sha256": "1d8d813f79ce21bce2926cd1549920d1200a99d2cedf05bf70afef94761c7f4b",
        "url": "https://nexus.microbot.cloud/repository/microbot-plugins/net/runelite/client/plugins/microbot/motherloadmineplugin/1.8.1/motherloadmineplugin-1.8.1.jar"
    },
    {
        "internalName": "ShootingStarPlugin",
        "name": "ShootingStar",
        "description": "Finds & Travels to shooting stars",
        "tags": [
            "mining",
            "skilling",
            "star",
            "shooting"
        ],
        "version": "1.4.2",
        "minClientVersion": "1.9.8",
        "authors": [
            "g-mason0"
        ],
        "iconUrl": "https://chsami.github.io/Microbot-Hub/ShootingStarPlugin/assets/icon.png",
        "cardUrl": "https://chsami.github.io/Microbot-Hub/ShootingStarPlugin/assets/card.png",
        "disable": false,
        "sha256": "44799021bb36bfc1b3ee1c0faa24e2d445d20c8b1f85cdd7756dcbe8fe2823f2",
        "url": "https://nexus.microbot.cloud/repository/microbot-plugins/net/runelite/client/plugins/microbot/shootingstarplugin/1.4.2/shootingstarplugin-1.4.2.jar"
    },
    {
        "internalName": "TitheFarmingPlugin",
        "name": "Tithe Farm",
        "description": "Plays the Tithe farm minigame for you!",
        "tags": [
            "tithe farming",
            "microbot",
            "skills",
            "minigame"
        ],
        "version": "1.1.1",
        "minClientVersion": "1.9.8.8",
        "authors": [
            "Mocrosoft"
        ],
        "iconUrl": "https://chsami.github.io/Microbot-Hub/TitheFarmingPlugin/assets/icon.png",
        "cardUrl": "https://chsami.github.io/Microbot-Hub/TitheFarmingPlugin/assets/card.png",
        "disable": false,
        "sha256": "3ddbd9e36e0e95d680d9691e7513597159c8fdf225b0d963c62c77e31e316d19",
        "url": "https://nexus.microbot.cloud/repository/microbot-plugins/net/runelite/client/plugins/microbot/tithefarmingplugin/1.1.1/tithefarmingplugin-1.1.1.jar"
    },
    {
        "internalName": "CannonballSmelterPlugin",
        "name": "Cannonball Smelter",
        "description": "Makes cannonballs",
        "tags": [
            "smithing",
            "girdy",
            "skilling"
        ],
        "version": "1.1.0",
        "minClientVersion": "1.9.9.1",
        "authors": [
            "Girdy",
            "Engin"
        ],
        "iconUrl": "https://chsami.github.io/Microbot-Hub/CannonballSmelterPlugin/assets/icon.png",
        "cardUrl": "https://chsami.github.io/Microbot-Hub/CannonballSmelterPlugin/assets/card.png",
        "disable": false,
        "sha256": "419b4aee7d588b8ed7e5fa115cd00324f298a6a9cdc2a46e33e7af151f7f4631",
        "url": "https://nexus.microbot.cloud/repository/microbot-plugins/net/runelite/client/plugins/microbot/cannonballsmelterplugin/1.1.0/cannonballsmelterplugin-1.1.0.jar"
    },
    {
        "internalName": "AutoFishingPlugin",
        "name": "Fishing",
        "description": "Automated fishing plugin with banking support",
        "tags": [
            "fishing",
            "skilling"
        ],
        "version": "1.0.1",
        "minClientVersion": "1.9.8",
        "authors": [
            "Unknown"
        ],
        "iconUrl": "https://chsami.github.io/Microbot-Hub/AutoFishingPlugin/assets/icon.png",
        "cardUrl": "https://chsami.github.io/Microbot-Hub/AutoFishingPlugin/assets/card.png",
        "disable": false,
        "sha256": "7c2aa1cde8e604001f5b639bebe976409efe4c0149bbc44e187da36bd299ece0",
        "url": "https://nexus.microbot.cloud/repository/microbot-plugins/net/runelite/client/plugins/microbot/autofishingplugin/1.0.1/autofishingplugin-1.0.1.jar"
    },
    {
        "internalName": "AnonymousPlugin",
        "name": "Anonymous Mode",
        "description": "Hide your in-game identity.",
        "tags": [
            "chat",
            "mask",
            "hide",
            "anonymous"
        ],
        "version": "1.0.3",
        "minClientVersion": "1.9.6",
        "authors": [
            "Bolado"
        ],
        "iconUrl": "https://chsami.github.io/Microbot-Hub/AnonymousPlugin/assets/icon.png",
        "cardUrl": "https://chsami.github.io/Microbot-Hub/AnonymousPlugin/assets/card.png",
        "disable": false,
        "sha256": "a586a97c757f3c86c45154fd3f06bf068d5f59a9d16d87657f1d5b8b41a8222e",
        "url": "https://nexus.microbot.cloud/repository/microbot-plugins/net/runelite/client/plugins/microbot/anonymousplugin/1.0.3/anonymousplugin-1.0.3.jar"
    },
    {
        "internalName": "JewelleryEnchantPlugin",
        "name": "Jewellery Enchant",
        "description": "Enchants all types of jewellery, with smart staff & rune handling.",
        "tags": [
            "magic",
            "enchant",
            "jewellery",
            "skilling",
            "microbot"
        ],
        "version": "1.0.1",
        "minClientVersion": "1.9.8",
        "authors": [
            "Lumusi"
        ],
        "iconUrl": "https://chsami.github.io/Microbot-Hub/JewelleryEnchantPlugin/assets/icon.png",
        "cardUrl": "https://chsami.github.io/Microbot-Hub/JewelleryEnchantPlugin/assets/card.png",
        "disable": false,
        "sha256": "477d6e5784370a27c13adeedb3b75df944d75a4bd820f60a05f31f6222d46056",
        "url": "https://nexus.microbot.cloud/repository/microbot-plugins/net/runelite/client/plugins/microbot/jewelleryenchantplugin/1.0.1/jewelleryenchantplugin-1.0.1.jar"
    },
    {
        "internalName": "ThievingPlugin",
        "name": "Thieving",
        "description": "Microbot thieving plugin",
        "tags": [
            "thieving",
            "skilling"
        ],
        "version": "2.0.3",
        "minClientVersion": "1.9.8.2",
        "authors": [
            "Mocrosoft",
            "Kryox",
            "Jesusfh"
        ],
        "iconUrl": "https://chsami.github.io/Microbot-Hub/ThievingPlugin/assets/icon.png",
        "cardUrl": "https://chsami.github.io/Microbot-Hub/ThievingPlugin/assets/card.png",
        "disable": false,
        "sha256": "882b2dadb184f44372a9f3923a5d1d1a1d36fcfdb69c2d7303d77c7ee24d235a",
        "url": "https://nexus.microbot.cloud/repository/microbot-plugins/net/runelite/client/plugins/microbot/thievingplugin/2.0.3/thievingplugin-2.0.3.jar"
    },
    {
        "internalName": "JadPlugin",
        "name": "Jad Helper",
        "description": "Auto prays jad attacks and attacks healers",
        "tags": [
            "jad",
            "microbot"
        ],
        "version": "1.0.6",
        "minClientVersion": "1.9.8.8",
        "authors": [
            "Mocrosoft"
        ],
        "iconUrl": "https://chsami.github.io/Microbot-Hub/JadPlugin/assets/icon.png",
        "cardUrl": "https://chsami.github.io/Microbot-Hub/JadPlugin/assets/card.png",
        "disable": false,
        "sha256": "725608f2ddf16e26e4e1d9a0daef8342890a00a826c5f463bf707f2c03f8a48f",
        "url": "https://nexus.microbot.cloud/repository/microbot-plugins/net/runelite/client/plugins/microbot/jadplugin/1.0.6/jadplugin-1.0.6.jar"
    },
    {
        "internalName": "AutoChompyKillerPlugin",
        "name": "Chompy Killer",
        "description": "Automated chompy bird hunting plugin...",
        "tags": [
            "chompy",
            "combat"
        ],
        "version": "1.0.1",
        "minClientVersion": "1.9.8",
        "authors": [
            "Unknown"
        ],
        "iconUrl": "https://chsami.github.io/Microbot-Hub/AutoChompyKillerPlugin/assets/icon.png",
        "cardUrl": "https://chsami.github.io/Microbot-Hub/AutoChompyKillerPlugin/assets/card.png",
        "disable": false,
        "sha256": "8c63551b84d605fedd92609dfa1f0fa855de49c7ca1895afc56d2b6c4bc97129",
        "url": "https://nexus.microbot.cloud/repository/microbot-plugins/net/runelite/client/plugins/microbot/autochompykillerplugin/1.0.1/autochompykillerplugin-1.0.1.jar"
    },
    {
        "internalName": "AutoBankStanderPlugin",
        "name": "Bank Stander",
        "description": "AIO bank standing plugin for various processing activities",
        "tags": [
            "magic",
            "skilling",
            "processing"
        ],
        "version": "1.0.2",
        "minClientVersion": "1.9.8",
        "authors": [
            "Unknown"
        ],
        "iconUrl": "https://chsami.github.io/Microbot-Hub/AutoBankStanderPlugin/assets/icon.png",
        "cardUrl": "https://chsami.github.io/Microbot-Hub/AutoBankStanderPlugin/assets/card.png",
        "disable": false,
        "sha256": "c74cf39f6d53cc34d33ac8bdc181edff00626e194a09da839753a8429e4da92b",
        "url": "https://nexus.microbot.cloud/repository/microbot-plugins/net/runelite/client/plugins/microbot/autobankstanderplugin/1.0.2/autobankstanderplugin-1.0.2.jar"
    },
    {
        "internalName": "TutorialIslandPlugin",
        "name": "Tutorial Island",
        "description": "Microbot Tutorial Island plugin",
        "tags": [
            "TutorialIsland",
            "microbot"
        ],
        "version": "1.3",
        "minClientVersion": "1.9.9.1",
        "authors": [
            "Mocrosoft"
        ],
        "iconUrl": "https://chsami.github.io/Microbot-Hub/TutorialIslandPlugin/assets/icon.png",
        "cardUrl": "https://chsami.github.io/Microbot-Hub/TutorialIslandPlugin/assets/card.png",
        "disable": false,
        "sha256": "2ee9969e1435c2ae172028b48fd3adbdf9bc4997f90e3998d1be2ca84e520a16",
        "url": "https://nexus.microbot.cloud/repository/microbot-plugins/net/runelite/client/plugins/microbot/tutorialislandplugin/1.3/tutorialislandplugin-1.3.jar"
    },
    {
        "internalName": "VarrockAnvilPlugin",
        "name": "Varrock Anvil",
        "description": "Smith items at the anvils in Varrock West.",
        "tags": [
            "smithing",
            "varrock",
            "anvil"
        ],
        "version": "1.0.3",
        "minClientVersion": "1.9.6",
        "authors": [
            "StickToTheScript"
        ],
        "iconUrl": "https://chsami.github.io/Microbot-Hub/VarrockAnvilPlugin/assets/icon.png",
        "cardUrl": "https://chsami.github.io/Microbot-Hub/VarrockAnvilPlugin/assets/card.png",
        "disable": false,
        "sha256": "aaf5bc8f2616a0ec7c47af082f49e089090a73f712e7c2fe7c234f45fecfbc92",
        "url": "https://nexus.microbot.cloud/repository/microbot-plugins/net/runelite/client/plugins/microbot/varrockanvilplugin/1.0.3/varrockanvilplugin-1.0.3.jar"
    },
    {
        "internalName": "BonesToBananasPlugin",
        "name": "Bones to Bananas",
        "description": "Casts Bones to Bananas, using staves to save runes.",
        "tags": [
            "magic",
            "skilling",
            "bones",
            "bananas",
            "microbot"
        ],
        "version": "1.0.1",
        "minClientVersion": "1.9.8",
        "authors": [
            "Lumusi"
        ],
        "iconUrl": "https://chsami.github.io/Microbot-Hub/BonesToBananasPlugin/assets/icon.png",
        "cardUrl": "https://chsami.github.io/Microbot-Hub/BonesToBananasPlugin/assets/card.png",
        "disable": false,
        "sha256": "0a281258004c06274f068ab4f4c1b5eadb27d18e18c9342a10b8ea2d1d54c580",
        "url": "https://nexus.microbot.cloud/repository/microbot-plugins/net/runelite/client/plugins/microbot/bonestobananasplugin/1.0.1/bonestobananasplugin-1.0.1.jar"
    },
    {
        "internalName": "PestControlPlugin",
        "name": "Pest Control",
        "description": "Supports all boats, portals, and shields.",
        "tags": [
            "pest control",
            "minigames"
        ],
        "version": "2.2.6",
        "minClientVersion": "1.9.6",
        "authors": [
            "Mocrosoft"
        ],
        "iconUrl": "https://chsami.github.io/Microbot-Hub/PestControlPlugin/assets/icon.png",
        "cardUrl": "https://chsami.github.io/Microbot-Hub/PestControlPlugin/assets/card.png",
        "disable": false,
        "sha256": "c2ef2c5967e4872055430ca47dbbbdc538c669a54b1634e9a354bf7fe437b329",
        "url": "https://nexus.microbot.cloud/repository/microbot-plugins/net/runelite/client/plugins/microbot/pestcontrolplugin/2.2.6/pestcontrolplugin-2.2.6.jar"
    },
    {
        "internalName": "WildernessAgilityPlugin",
        "name": "Wilderness Agility",
        "description": "Automated wilderness agility training with banking and ticket collection",
        "tags": [
            "agility",
            "skilling",
            "solo",
            "mass",
            "MoneyMaking"
        ],
        "version": "1.5.1",
        "minClientVersion": "1.9.8",
        "authors": [
            "Unknown Author"
        ],
        "iconUrl": "https://chsami.github.io/Microbot-Hub/WildernessAgilityPlugin/assets/Icon.png",
        "cardUrl": "httpa://chsami.github.io/Microbot-Hub/WildernessAgilityPlugin/assets/Card.png",
        "disable": false,
        "sha256": "cf9401a3e65c246e4bc98eb8df9f8aa70af3436af0bd54d87948ead590ac00ae",
        "url": "https://nexus.microbot.cloud/repository/microbot-plugins/net/runelite/client/plugins/microbot/wildernessagilityplugin/1.5.1/wildernessagilityplugin-1.5.1.jar"
    },
    {
        "internalName": "TowerOfLifeCCPlugin",
        "name": " Creature Creation",
        "description": "Automates the creature creation process within the Tower of Life basement.",
        "tags": [
            "Tower of life",
            "creature",
            "creature creation",
            "creation",
            "tol",
            "cc",
            "cd",
            "cardew"
        ],
        "version": "1.1.4",
        "minClientVersion": "1.9.8",
        "authors": [
            "Cardew"
        ],
        "iconUrl": "https://chsami.github.io/Microbot-Hub/TowerOfLifeCCPlugin/assets/icon.png",
        "cardUrl": "https://chsami.github.io/Microbot-Hub/TowerOfLifeCCPlugin/assets/card.png",
        "disable": false,
        "sha256": "5a967ed17e979671e7d6b772d9bebdd0f00c4c9715dfde33faea032952d6f00b",
        "url": "https://nexus.microbot.cloud/repository/microbot-plugins/net/runelite/client/plugins/microbot/toweroflifeccplugin/1.1.4/toweroflifeccplugin-1.1.4.jar"
    },
    {
        "internalName": "BankSellerPlugin",
        "name": "Bank Seller",
        "description": "Withdraws tradeable bank items and sells them on the Grand Exchange",
        "tags": [
            "bank",
            "ge",
            "seller"
        ],
        "version": "1.0.2",
        "minClientVersion": "1.9.8",
        "authors": [
            "KSP"
        ],
        "iconUrl": "https://chsami.github.io/Microbot-Hub/BankSellerPlugin/assets/bank.png",
        "cardUrl": "https://chsami.github.io/Microbot-Hub/BankSellerPlugin/assets/card.png",
        "disable": false,
        "sha256": "2ffb7cf0206c6e61a2eb6fd0ea1f3a0a087d56c865109493917d4388bfb86c1e",
        "url": "https://nexus.microbot.cloud/repository/microbot-plugins/net/runelite/client/plugins/microbot/banksellerplugin/1.0.2/banksellerplugin-1.0.2.jar"
    },
    {
        "internalName": "TheMessPlugin",
        "name": "The Mess",
        "description": "A plugin to automate cooking in The Mess hall.",
        "tags": [
            "cooking",
            "skilling",
            "microbot"
        ],
        "version": "1.0.2",
        "minClientVersion": "1.9.8",
        "authors": [
            "Bolado"
        ],
        "iconUrl": "https://chsami.github.io/Microbot-Hub/TheMessPlugin/assets/icon.png",
        "cardUrl": "https://chsami.github.io/Microbot-Hub/TheMessPlugin/assets/card.png",
        "disable": false,
        "sha256": "4d56afd916564cb147ba47ea17ee9751b7d9fc8a98c7595bfd9eaa30f2930e09",
        "url": "https://nexus.microbot.cloud/repository/microbot-plugins/net/runelite/client/plugins/microbot/themessplugin/1.0.2/themessplugin-1.0.2.jar"
    },
    {
        "internalName": "CharterCrafterPlugin",
        "name": "Charter Crafter",
        "description": "Charter crafting plugin (UIM-friendly)",
        "tags": [
            "charter",
            "crafting"
        ],
        "version": "1.0.0",
        "minClientVersion": "1.9.8",
        "authors": [
            "heapoverfl0w"
        ],
        "iconUrl": "https://chsami.github.io/Microbot-Hub/CharterCrafterPlugin/assets/icon.png",
        "cardUrl": "https://chsami.github.io/Microbot-Hub/CharterCrafterPlugin/assets/card.png",
        "disable": false,
        "sha256": "8903dd085451bbc7d70fb51146f6241aa9337f2b41fcf18853bc329e664e9d7d",
        "url": "https://nexus.microbot.cloud/repository/microbot-plugins/net/runelite/client/plugins/microbot/chartercrafterplugin/1.0.0/chartercrafterplugin-1.0.0.jar"
    },
    {
        "internalName": "HerbiboarPlugin",
        "name": "Herbiboar",
        "description": "Automatically hunts herbiboars with trail tracking and banking support",
        "tags": [
            "skilling",
            "hunter",
            "herbiboar"
        ],
        "version": "1.2.3",
        "minClientVersion": "1.9.8",
        "authors": [
            "AI Agent"
        ],
        "iconUrl": "https://chsami.github.io/Microbot-Hub/HerbiboarPlugin/assets/icon.png",
        "cardUrl": "https://chsami.github.io/Microbot-Hub/HerbiboarPlugin/assets/card.png",
        "disable": false,
        "sha256": "f5e20265108979bd1d6fcc7c9f914c265f75ecf89593984001d30a86852f30ad",
        "url": "https://nexus.microbot.cloud/repository/microbot-plugins/net/runelite/client/plugins/microbot/herbiboarplugin/1.2.3/herbiboarplugin-1.2.3.jar"
    },
    {
        "internalName": "NmzPlugin",
        "name": "Nmz",
        "description": "Plays the nightmare zone minigame",
        "tags": [
            "nmz",
            "microbot"
        ],
        "version": "2.2.0",
        "minClientVersion": "1.9.8",
        "authors": [
            "Mocrosoft"
        ],
        "iconUrl": "https://chsami.github.io/Microbot-Hub/NmzPlugin/assets/icon.png",
        "cardUrl": "https://chsami.github.io/Microbot-Hub/NmzPlugin/assets/card.png",
        "disable": false,
        "sha256": "e019fa9837af343cd582990fd3bd4400dccb378c9c2e9bff7eaffa119cae0490",
        "url": "https://nexus.microbot.cloud/repository/microbot-plugins/net/runelite/client/plugins/microbot/nmzplugin/2.2.0/nmzplugin-2.2.0.jar"
    },
    {
        "internalName": "MixologyPlugin",
        "name": "Mixology",
        "description": "Mixology plugin",
        "tags": [
            "herblore",
            "microbot",
            "mixology"
        ],
        "version": "1.0.2-beta",
        "minClientVersion": "1.9.9.1",
        "authors": [
            "Mocrosoft"
        ],
        "iconUrl": "https://chsami.github.io/Microbot-Hub/MixologyPlugin/assets/icon.png",
        "cardUrl": "https://chsami.github.io/Microbot-Hub/MixologyPlugin/assets/card.png",
        "disable": false,
        "sha256": "85f61c780160717fdcef106b6bc59e83f7592814aa87914eac99ddc0c0d770ca",
        "url": "https://nexus.microbot.cloud/repository/microbot-plugins/net/runelite/client/plugins/microbot/mixologyplugin/1.0.2-beta/mixologyplugin-1.0.2-beta.jar"
    },
    {
        "internalName": "MageTrainingArenaPlugin",
        "name": "Mage Training Arena",
        "description": "Basche's Mage Training Arena plugin",
        "tags": [
            "basche",
            "mta",
            "moneymaking",
            "magic"
        ],
        "version": "1.1.4",
        "minClientVersion": "1.9.8.8",
        "authors": [
            "Basche"
        ],
        "iconUrl": "https://chsami.github.io/Microbot-Hub/MageTrainingArenaPlugin/assets/icon.png",
        "cardUrl": "https://chsami.github.io/Microbot-Hub/MageTrainingArenaPlugin/assets/card.png",
        "disable": false,
        "sha256": "ad4e9f7b6f837c09cf22a4caa0bfed6c9122900bd769d0bdae9505e18999f29c",
        "url": "https://nexus.microbot.cloud/repository/microbot-plugins/net/runelite/client/plugins/microbot/magetrainingarenaplugin/1.1.4/magetrainingarenaplugin-1.1.4.jar"
    },
    {
        "internalName": "GEFiremakerPlugin",
        "name": "GE Firemaker",
        "description": "Uses logs on campfires around the Grand Exchange.",
        "tags": [
            "firemaking",
            "campfire",
            "grand",
            "exchange",
            "ge"
        ],
        "version": "1.0.1",
        "minClientVersion": "1.9.6",
        "authors": [
            "StickToTheScript"
        ],
        "iconUrl": "https://chsami.github.io/Microbot-Hub/GEFiremakerPlugin/assets/firemaking.png",
        "cardUrl": "https://chsami.github.io/Microbot-Hub/GEFiremakerPlugin/assets/card.png",
        "disable": false,
        "sha256": "b7ee4ad9b438953c150065a854ddd45aec050ea0db311e38e624f6d3ec8a5995",
        "url": "https://nexus.microbot.cloud/repository/microbot-plugins/net/runelite/client/plugins/microbot/gefiremakerplugin/1.0.1/gefiremakerplugin-1.0.1.jar"
    },
    {
        "internalName": "ExamplePlugin",
        "name": "Example",
        "description": "Microbot Example Plugin",
        "tags": [
            "example"
        ],
        "version": "1.1.1",
        "minClientVersion": "1.9.8",
        "authors": [
            "Mocrosoft"
        ],
        "iconUrl": "",
        "cardUrl": "",
        "disable": true,
        "sha256": "badb406789ee3351e37f7b19cceb2fc5509ffb1535d7bba010d98b699a68bdd9",
        "url": "https://nexus.microbot.cloud/repository/microbot-plugins/net/runelite/client/plugins/microbot/exampleplugin/1.1.1/exampleplugin-1.1.1.jar"
    },
    {
        "internalName": "MKE_WintertodtPlugin",
        "name": " AI-Wintertodt",
        "description": "Advanced Wintertodt bot with human-like behavior",
        "tags": [
            "Wintertodt",
            "firemaking",
            "minigame"
        ],
        "version": "2.1.0",
        "minClientVersion": "1.9.7",
        "authors": [
            "Make"
        ],
        "iconUrl": "https://chsami.github.io/Microbot-Hub/MKE_WintertodtPlugin/assets/card.png",
        "cardUrl": "https://chsami.github.io/Microbot-Hub/MKE_WintertodtPlugin/assets/card.png",
        "disable": false,
        "sha256": "746d69f4e40f46a08599248d8e6c4f1d1c9a439c1a4760a8994b37d6569319ca",
        "url": "https://nexus.microbot.cloud/repository/microbot-plugins/net/runelite/client/plugins/microbot/mke_wintertodtplugin/2.1.0/mke_wintertodtplugin-2.1.0.jar"
    },
    {
        "internalName": "GECookerPlugin",
        "name": "GE Cooker",
        "description": "Cooks items on fires found at the Grand Exchange.",
        "tags": [
            "cooking",
            "grand",
            "exchange",
            "ge",
            "fish",
            "raw"
        ],
        "version": "1.0.1",
        "minClientVersion": "1.9.6",
        "authors": [
            "StickToTheScript"
        ],
        "iconUrl": "https://chsami.github.io/Microbot-Hub/GECookerPlugin/assets/cooking.png",
        "cardUrl": "https://chsami.github.io/Microbot-Hub/GECookerPlugin/assets/card.png",
        "disable": false,
        "sha256": "ad11dc1f4ec622473c121449edf4554f0b466b52efa8e550b661a03f24854e26",
        "url": "https://nexus.microbot.cloud/repository/microbot-plugins/net/runelite/client/plugins/microbot/gecookerplugin/1.0.1/gecookerplugin-1.0.1.jar"
    },
    {
        "internalName": "ValeTotemPlugin",
        "name": "Vale Totems",
        "description": "Automated Vale Totems minigame bot with advanced optimizations",
        "tags": [
            "valetotems",
            "fletching",
            "minigame"
        ],
        "version": "1.0.3",
        "minClientVersion": "1.9.7",
        "authors": [
            "Make"
        ],
        "iconUrl": "https://chsami.github.io/Microbot-Hub/ValeTotemPlugin/assets/card.png",
        "cardUrl": "https://chsami.github.io/Microbot-Hub/ValeTotemPlugin/assets/card.png",
        "disable": false,
        "sha256": "3d1e239f7293c66e97886e42615a48478d92452fcfdddafd02efc69f84818d1e",
        "url": "https://nexus.microbot.cloud/repository/microbot-plugins/net/runelite/client/plugins/microbot/valetotemplugin/1.0.3/valetotemplugin-1.0.3.jar"
    },
    {
        "internalName": "BlessedWinePlugin",
        "name": "Blessed Wine",
        "description": "Automating Prayer Training using blessed wines at Cam Torum",
        "tags": [
            "blessed",
            "wine",
            "ralos",
            "prayer",
            "libation"
        ],
        "version": "1.0.2",
        "minClientVersion": "1.9.6",
        "authors": [
            "Hal"
        ],
        "iconUrl": "https://oldschool.runescape.wiki/images/Jug_of_wine.png",
        "cardUrl": "",
        "disable": false,
        "sha256": "a88fea7a2830750581f4dff17b3e14b685e28fed304b89ccca2177671a48c3f2",
        "url": "https://nexus.microbot.cloud/repository/microbot-plugins/net/runelite/client/plugins/microbot/blessedwineplugin/1.0.2/blessedwineplugin-1.0.2.jar"
    },
    {
        "internalName": "FletchingPlugin",
        "name": "Fletcher",
        "description": "Microbot fletching plugin",
        "tags": [
            "fletching",
            "microbot",
            "skills"
        ],
        "version": "1.6.2",
        "minClientVersion": "1.9.9.1",
        "authors": [
            "Mocrosoft"
        ],
        "iconUrl": "https://chsami.github.io/Microbot-Hub/FletchingPlugin/assets/icon.png",
        "cardUrl": "https://chsami.github.io/Microbot-Hub/FletchingPlugin/assets/card.png",
        "disable": false,
        "sha256": "cc250e500ed0e0e62fbc75e543259affaa052881161220cebcd3b4d9e0df9718",
        "url": "https://nexus.microbot.cloud/repository/microbot-plugins/net/runelite/client/plugins/microbot/fletchingplugin/1.6.2/fletchingplugin-1.6.2.jar"
    },
    {
        "internalName": "OuraniaPlugin",
        "name": "Ourania Altar",
        "description": "Craft runes at the Ourania Altar",
        "tags": [
            "runecrafting",
            "skilling",
            "ourania",
            "zmi"
        ],
        "version": "1.4.2",
        "minClientVersion": "1.9.8",
        "authors": [
            "g-mason0"
        ],
        "iconUrl": "https://chsami.github.io/Microbot-Hub/OuraniaPlugin/assets/icon.png",
        "cardUrl": "https://chsami.github.io/Microbot-Hub/OuraniaPlugin/assets/card.png",
        "disable": false,
        "sha256": "2d473611540227ecb598287ce8a3d507cf31082235bcbe72a6985127f1f00813",
        "url": "https://nexus.microbot.cloud/repository/microbot-plugins/net/runelite/client/plugins/microbot/ouraniaplugin/1.4.2/ouraniaplugin-1.4.2.jar"
    },
    {
        "internalName": "BarbarianVillageFisherPlugin",
        "name": "Barb Village Fisher",
        "description": "Fly and bait fish in Barbarian Village.",
        "tags": [
            "fish",
            "fishing",
            "fly",
            "bait",
            "barb",
            "barbarian",
            "village"
        ],
        "version": "1.0.1",
        "minClientVersion": "1.9.6",
        "authors": [
            "StickToTheScript"
        ],
        "iconUrl": "https://chsami.github.io/Microbot-Hub/BarbarianVillageFisherPlugin/assets/icon.png",
        "cardUrl": "https://chsami.github.io/Microbot-Hub/BarbarianVillageFisherPlugin/assets/card.png",
        "disable": false,
        "sha256": "5d145731a8f1b4453f45f2030131c40cc3cd98a621d7a2a191129a446d612f4c",
        "url": "https://nexus.microbot.cloud/repository/microbot-plugins/net/runelite/client/plugins/microbot/barbarianvillagefisherplugin/1.0.1/barbarianvillagefisherplugin-1.0.1.jar"
    },
    {
        "internalName": "ArceuusRcPlugin",
        "name": "Arceuus RC",
        "description": "Runecrafting at Arceuus",
        "tags": [
            "runecrafting",
            "blood rune",
            "soul rune",
            "arceuus",
            "microbot"
        ],
        "version": "1.0.2",
        "minClientVersion": "1.9.9.1",
        "authors": [
            "See1Duck"
        ],
        "iconUrl": "https://chsami.github.io/Microbot-Hub/ArceuusRcPlugin/assets/icon.png",
        "cardUrl": "https://chsami.github.io/Microbot-Hub/ArceuusRcPlugin/assets/card.png",
        "disable": false,
        "sha256": "ca97f0a775e213aef86728cb359775b06fa6492d1f8d47c00c20e601f5e04561",
        "url": "https://nexus.microbot.cloud/repository/microbot-plugins/net/runelite/client/plugins/microbot/arceuusrcplugin/1.0.2/arceuusrcplugin-1.0.2.jar"
    }
]